stacks/__init__.py
stacks/database.py
stacks/events.py
stacks/job.py
stacks/package.py
stacks/util.py
stacks/web.py
python_stacks-0.0.1.dist-info/METADATA
python_stacks-0.0.1.dist-info/WHEEL
python_stacks-0.0.1.dist-info/top_level.txt
python_stacks-0.0.1.dist-info/RECORD
