Metadata-Version: 2.1
Name: python-stacks
Version: 0.0.1
Summary: A utility for interacting with insteon modems and hubs
Home-page: https://github.com/pfrommerd/stacks
Author: Daniel Pfrommer
License: UNKNOWN
Project-URL: Source, https://github.com/pfrommerd/stacks/
Keywords: packaging
Platform: UNKNOWN
Classifier: Development Status :: 3 - Alpha
Classifier: Intended Audience :: Developers
Classifier: Topic :: Software Development :: Build Tools
Classifier: License :: OSI Approved :: MIT License
Classifier: Programming Language :: Python :: 3
Classifier: Programming Language :: Python :: 3.6
Classifier: Operating System :: OS Independent
Provides-Extra: dev
Provides-Extra: test
